setup.py
lingu/__init__.py
lingu/main.py
lingu/correctors/__init__.py
lingu/correctors/reynir.py
lingu/correctors/text.py
lingu/ocr/__init__.py
lingu/ocr/general.py
lingu/ocr/ngrams.py
lingu/ocr/postprocessing.py
lingu/ocr/reynir.py
lingu-0.1.1.dist-info/LICENSE
lingu-0.1.1.dist-info/METADATA
lingu-0.1.1.dist-info/WHEEL
lingu-0.1.1.dist-info/top_level.txt
lingu-0.1.1.dist-info/zip-safe
lingu-0.1.1.dist-info/RECORD
